flask_pdf_extractor/__init__.py
flask_pdf_extractor/app.py
flask_pdf_extractor-1.0.0.dist-info/METADATA
flask_pdf_extractor-1.0.0.dist-info/WHEEL
flask_pdf_extractor-1.0.0.dist-info/entry_points.txt
flask_pdf_extractor-1.0.0.dist-info/top_level.txt
flask_pdf_extractor-1.0.0.dist-info/RECORD
