Metadata-Version: 2.1
Name: flask-pdf-extractor
Version: 1.0.0
Summary: pdf extraction package
Author: bhavesh_kumar
Author-email: kumarbhavesh8298@gmail.com
Classifier: Programming Language :: Python :: 3
Classifier: License :: OSI Approved :: MIT License
Classifier: Operating System :: OS Independent
Requires-Python: >=3.10
Requires-Dist: Flask
Requires-Dist: PyPDF2
Requires-Dist: ollama
Requires-Dist: python-dotenv
